[
    {
        "class":"CannyDain\\ShortyModules\\Comments\\Models\\Comment",
        "auto_id":"id",
        "id":
        [
            "id"
        ],
        "table":"comments",
        "fields":
        [
            {
                "column":"id",
                "type":"int",
                "property":"_id",
                "size":11
            },
            {
                "column":"guid",
                "type":"varchar",
                "property":"_guid",
                "size":500
            },
            {
                "column":"posted",
                "type":"datetime",
                "property":"_postedAt",
                "size":0
            },
			{
                "column":"subject",
                "type":"varchar",
                "property":"_subject",
                "size":500
            },
            {
                "column":"comment",
                "type":"text",
                "property":"_comment",
                "size":0
            },
            {
                "column":"author",
                "type":"varchar",
                "property":"_author",
                "size":200
            },
			{
                "column":"read",
                "type":"int",
                "property":"_read",
                "size":0
            }
        ]
    }
]